source_jira/__init__.py
source_jira/components/__init__.py
source_jira/components/extractors.py
source_jira/components/partition_routers.py
source_jira/components/transformations.py
source_jira/manifest.yaml
source_jira/run.py
source_jira/schemas/application_roles.json
source_jira/schemas/audit_records.json
source_jira/schemas/avatars.json
source_jira/schemas/board_issues.json
source_jira/schemas/boards.json
source_jira/schemas/dashboards.json
source_jira/schemas/dynamic_modules.json
source_jira/schemas/filter_sharing.json
source_jira/schemas/filters.json
source_jira/schemas/groups.json
source_jira/schemas/issue_comment_properties.json
source_jira/schemas/issue_comments.json
source_jira/schemas/issue_custom_field_contexts.json
source_jira/schemas/issue_custom_field_options.json
source_jira/schemas/issue_custom_field_options_apps.json
source_jira/schemas/issue_field_configurations.json
source_jira/schemas/issue_fields.json
source_jira/schemas/issue_link_types.json
source_jira/schemas/issue_navigator_settings.json
source_jira/schemas/issue_notification_schemes.json
source_jira/schemas/issue_priorities.json
source_jira/schemas/issue_properties.json
source_jira/schemas/issue_remote_links.json
source_jira/schemas/issue_resolutions.json
source_jira/schemas/issue_security_schemes.json
source_jira/schemas/issue_transitions.json
source_jira/schemas/issue_type_properties.json
source_jira/schemas/issue_type_schemes.json
source_jira/schemas/issue_type_screen_schemes.json
source_jira/schemas/issue_types.json
source_jira/schemas/issue_votes.json
source_jira/schemas/issue_watchers.json
source_jira/schemas/issue_worklogs.json
source_jira/schemas/issues.json
source_jira/schemas/jira_settings.json
source_jira/schemas/jql.json
source_jira/schemas/labels.json
source_jira/schemas/permission_schemes.json
source_jira/schemas/permissions.json
source_jira/schemas/project_avatars.json
source_jira/schemas/project_categories.json
source_jira/schemas/project_components.json
airbyte_source_jira-4.0.0.dist-info/METADATA
airbyte_source_jira-4.0.0.dist-info/WHEEL
airbyte_source_jira-4.0.0.dist-info/entry_points.txt
airbyte_source_jira-4.0.0.dist-info/RECORD
